LICENSE
mapdataset/__init__.py
mapdataset/lib/__init__.py
mapdataset/lib/ImageGroupReader.py
mapdataset/lib/ImageUtils.py
mapdataset/lib/maps.py
mapdataset/osm2graphdata.py
mapdataset/osm2imgdata.py
mapdataset/readmbtiles.py
mapdataset/sliceimages.py
mapdatasetgenerator-0.0.2.dist-info/LICENSE
mapdatasetgenerator-0.0.2.dist-info/WHEEL
mapdatasetgenerator-0.0.2.dist-info/METADATA
mapdatasetgenerator-0.0.2.dist-info/RECORD
