Metadata-Version: 2.1
Name: mapdatasetgenerator
Version: 0.0.2
Summary: Map dataset generator for learning map representations and generation
Home-page: https://github.com/AugmentedDesignLab/MapDatasetGenerator
License: Mozilla Public License Version 2.0
Keywords: Map Dataset,OSM to image
Author: Ishaan
Author-email: iparanja@ucsc.edu
Requires-Python: >=3.7.9,<4.0.0
Classifier: License :: Other/Proprietary License
Classifier: Programming Language :: Python :: 3
Classifier: Programming Language :: Python :: 3.8
Classifier: Programming Language :: Python :: 3.9
Classifier: Programming Language :: Python :: 3.10
Requires-Dist: Pillow (>=9.2.0,<10.0.0)
Requires-Dist: dill (>=0.3.5.1,<0.4.0.0)
Requires-Dist: mbutil (>=0.3.0,<0.4.0)
Requires-Dist: torch (>=1.12.1,<2.0.0)
Requires-Dist: tqdm (>=4.64.1,<5.0.0)
Project-URL: Repository, https://github.com/AugmentedDesignLab/MapDatasetGenerator
